[
  {
    "id": "hitchcock",
    "active": true,
    "type": "Director",
    "name": "Alfred Hitchcock",
    "shortName": "Hitchcock",
    "desc": "The Master of Suspense — four decades of psychological thrillers that redefined cinema's capacity for dread.",
    "match": {
      "type": "name_in_credits",
      "value": "Alfred Hitchcock",
      "fields": [
        "dir",
        "actor",
        "supp",
        "cast"
      ]
    },
    "personId": 2636,
    "years": "1925–1976",
    "customImage": "images/hubs/hitchcock.jpg"
  },
  {
    "id": "mel-brooks",
    "active": true,
    "type": "Director",
    "name": "Mel Brooks",
    "shortName": "Mel Brooks",
    "desc": "Hollywood's great satirist — fearless, irreverent, and funnier than anyone who ever pointed a camera.",
    "match": {
      "type": "name_in_credits",
      "value": "Mel Brooks",
      "fields": [
        "dir",
        "actor",
        "supp",
        "cast"
      ]
    },
    "personId": 14639,
    "years": "1967–1995",
    "customImage": "images/hubs/mel-brooks.jpg"
  },
  {
    "id": "wes-anderson",
    "active": true,
    "type": "Director",
    "name": "Wes Anderson",
    "shortName": "Wes Anderson",
    "desc": "The most meticulously designed films in American cinema — symmetrical, melancholic, and utterly singular.",
    "match": {
      "type": "name_in_credits",
      "value": "Wes Anderson",
      "fields": [
        "dir",
        "actor",
        "supp",
        "cast"
      ]
    },
    "personId": 5655,
    "years": "1996–Present",
    "customImage": "images/hubs/wes-anderson.jpg"
  },
  {
    "id": "zucker-abrahams",
    "active": true,
    "type": "Director Collection",
    "name": "Zucker / Abrahams",
    "shortName": "Zucker / Abrahams",
    "desc": "The kings of parody — Airplane!, The Naked Gun, Hot Shots! and every gloriously absurd film in between.",
    "match": {
      "type": "compound",
      "any": [
        {
          "type": "name_in_credits",
          "value": "Abrahams",
          "fields": [
            "dir"
          ]
        },
        {
          "type": "name_in_credits",
          "value": "David Zucker",
          "fields": [
            "dir"
          ]
        },
        {
          "type": "name_in_credits",
          "value": "Jerry Zucker",
          "fields": [
            "dir"
          ]
        },
        {
          "type": "title_includes",
          "value": "Naked Gun"
        },
        {
          "type": "title_includes",
          "value": "Hot Shots"
        },
        {
          "type": "title_includes",
          "value": "Airplane"
        },
        {
          "type": "title_includes",
          "value": "Top Secret"
        }
      ]
    },
    "personId": 12936,
    "years": "1980–Present",
    "customImage": "images/hubs/zucker-abrahams.jpg"
  },
  {
    "id": "rob-reiner",
    "active": true,
    "type": "Director / Actor",
    "name": "Rob Reiner",
    "shortName": "Rob Reiner",
    "desc": "From Spinal Tap to Stand by Me to A Few Good Men — one of Hollywood's most versatile filmmakers.",
    "match": {
      "type": "name_in_credits",
      "value": "Rob Reiner",
      "fields": [
        "dir",
        "actor",
        "supp",
        "cast"
      ]
    },
    "personId": 3026,
    "years": "1984–Present",
    "customImage": "images/hubs/rob-reiner.jpg"
  },
  {
    "id": "john-hughes",
    "active": true,
    "type": "Director / Writer",
    "name": "John Hughes",
    "shortName": "John Hughes",
    "desc": "The poet laureate of the American teenager — and the architect of the perfect holiday comedy.",
    "match": {
      "type": "compound",
      "any": [
        {
          "type": "name_in_credits",
          "value": "John Hughes",
          "fields": [
            "dir"
          ]
        },
        {
          "type": "title_includes",
          "value": "Home Alone"
        },
        {
          "type": "title_includes",
          "value": "National Lampoon's Vacation"
        },
        {
          "type": "title_includes",
          "value": "Ferris Bueller"
        },
        {
          "type": "title_includes",
          "value": "Breakfast Club"
        },
        {
          "type": "title_includes",
          "value": "Sixteen Candles"
        },
        {
          "type": "title_includes",
          "value": "Pretty in Pink"
        },
        {
          "type": "title_includes",
          "value": "Planes, Trains"
        }
      ]
    },
    "personId": 11505,
    "years": "1983–1994",
    "customImage": "images/hubs/john-hughes.jpg"
  },
  {
    "id": "albert-brooks",
    "active": true,
    "type": "Director / Actor",
    "name": "Albert Brooks",
    "shortName": "Albert Brooks",
    "desc": "The neurotic's auteur — sharp, anxious comedies that cut closer to the bone than any of his contemporaries.",
    "match": {
      "type": "name_in_credits",
      "value": "Albert Brooks",
      "fields": [
        "dir",
        "actor",
        "supp",
        "cast"
      ]
    },
    "personId": 13,
    "years": "1979–2012",
    "customImage": "images/hubs/albert-brooks.jpg"
  },
  {
    "id": "robin-williams",
    "active": true,
    "type": "Artist Hub",
    "name": "Robin Williams",
    "shortName": "Robin Williams",
    "desc": "Boundless energy, bottomless heart — one of the most gifted performers ever to grace the screen.",
    "match": {
      "type": "name_in_credits",
      "value": "Robin Williams",
      "fields": [
        "actor",
        "supp",
        "cast"
      ]
    },
    "personId": 2157,
    "years": "1980–2014",
    "customImage": "images/hubs/robin-williams.jpg"
  },
  {
    "id": "sinatra",
    "active": true,
    "type": "Artist Hub",
    "name": "Frank Sinatra",
    "shortName": "Sinatra",
    "desc": "The Chairman of the Board on screen — Rat Pack cool, dramatic depth, and effortless screen presence.",
    "match": {
      "type": "name_in_credits",
      "value": "Frank Sinatra",
      "fields": [
        "actor",
        "supp",
        "cast"
      ]
    },
    "personId": 4347,
    "years": "1941–1980",
    "customImage": "images/hubs/sinatra.jpg"
  },
  {
    "id": "marx-brothers",
    "active": true,
    "type": "Ensemble",
    "name": "Marx Brothers",
    "shortName": "Marx Brothers",
    "desc": "Groucho, Harpo, and Chico — anarchic, absurdist, and utterly unstoppable. Comedy's most subversive act.",
    "match": {
      "type": "compound",
      "any": [
        {
          "type": "name_in_credits",
          "value": "Groucho",
          "fields": [
            "actor"
          ]
        },
        {
          "type": "name_in_credits",
          "value": "Harpo",
          "fields": [
            "actor"
          ]
        },
        {
          "type": "name_in_credits",
          "value": "Chico Marx",
          "fields": [
            "actor"
          ]
        }
      ]
    },
    "movieId": 442887,
    "years": "1929–1949",
    "customImage": "images/hubs/marx-brothers.jpg"
  },
  {
    "id": "paul-newman",
    "active": true,
    "type": "Artist Hub",
    "name": "Paul Newman",
    "shortName": "Paul Newman",
    "desc": "Cool, principled, and magnetic — one of Hollywood's greatest leading men across four decades.",
    "match": {
      "type": "name_in_credits",
      "value": "Paul Newman",
      "fields": [
        "actor",
        "supp",
        "cast"
      ]
    },
    "personId": 3636,
    "years": "1954–2006",
    "customImage": "images/hubs/paul-newman.jpg"
  },
  {
    "id": "de-niro",
    "active": true,
    "type": "Artist Hub",
    "name": "Robert De Niro",
    "shortName": "De Niro",
    "desc": "The defining actor of the New Hollywood era — ferocious, transformative, and utterly committed.",
    "match": {
      "type": "name_in_credits",
      "value": "Robert De Niro",
      "fields": [
        "actor",
        "supp",
        "cast"
      ]
    },
    "personId": 380,
    "years": "1968–Present",
    "customImage": "images/hubs/de-niro.jpg"
  },
  {
    "id": "jack-lemmon",
    "active": true,
    "type": "Artist Hub",
    "name": "Jack Lemmon",
    "shortName": "Jack Lemmon",
    "desc": "The everyman's actor — master of comedy and tragedy, the definitive collaborator of Billy Wilder's golden era.",
    "match": {
      "type": "compound",
      "all": [
        {
          "type": "name_in_credits",
          "value": "Jack Lemmon",
          "fields": [
            "actor",
            "supp",
            "cast"
          ]
        }
      ],
      "none": [
        {
          "type": "name_in_credits_lower",
          "value": "kasi lemmons",
          "fields": [
            "dir"
          ]
        }
      ]
    },
    "personId": 3151,
    "years": "1954–2001",
    "customImage": "images/hubs/jack-lemmon.jpg"
  },
  {
    "id": "poitier",
    "active": true,
    "type": "Artist Hub",
    "name": "Sidney Poitier",
    "shortName": "Sidney Poitier",
    "desc": "A towering presence who broke barriers and brought dignity, power, and grace to every role.",
    "match": {
      "type": "name_in_credits",
      "value": "Sidney Poitier",
      "fields": [
        "actor",
        "supp",
        "cast"
      ]
    },
    "personId": 16897,
    "years": "1950–2001",
    "customImage": "images/hubs/poitier.jpg"
  },
  {
    "id": "garner",
    "active": true,
    "type": "Artist Hub",
    "name": "James Garner",
    "shortName": "James Garner",
    "desc": "Hollywood's most likable rogue — effortlessly charming in westerns, comedies, and dramas across five decades.",
    "match": {
      "type": "name_in_credits",
      "value": "James Garner",
      "fields": [
        "actor",
        "supp",
        "cast"
      ]
    },
    "personId": 16896,
    "years": "1956–2013",
    "customImage": "images/hubs/garner.jpg"
  },
  {
    "id": "hope-crosby",
    "active": true,
    "type": "Partnership Hub",
    "name": "Hope & Crosby",
    "shortName": "Hope & Crosby",
    "desc": "Bob Hope and Bing Crosby — the Road Pictures partnership that defined Hollywood comedy for a generation.",
    "match": {
      "type": "compound",
      "any": [
        {
          "type": "name_in_credits",
          "value": "Bob Hope",
          "fields": [
            "actor",
            "supp"
          ]
        },
        {
          "type": "name_in_credits",
          "value": "Bing Crosby",
          "fields": [
            "actor",
            "supp"
          ]
        },
        {
          "type": "franchise_includes",
          "value": "Road"
        }
      ]
    },
    "collectionId": 135441,
    "years": "1934–1979",
    "customImage": "images/hubs/hope-crosby.jpg"
  },
  {
    "id": "gene-hackman",
    "active": true,
    "type": "Artist Hub",
    "name": "Gene Hackman",
    "shortName": "Hackman",
    "desc": "Five decades of unmatched character work — the most quietly brilliant actor of his generation.",
    "match": {
      "type": "name_in_credits",
      "value": "Gene Hackman",
      "fields": [
        "actor",
        "supp",
        "cast"
      ]
    },
    "personId": 193,
    "years": "1964–2004",
    "customImage": "images/hubs/gene-hackman.jpg"
  },
  {
    "id": "tom-hanks",
    "active": true,
    "type": "Artist Hub",
    "name": "Tom Hanks",
    "shortName": "Tom Hanks",
    "desc": "America's everyman — warmth, decency, and craft across four decades of indelible performances.",
    "match": {
      "type": "name_in_credits",
      "value": "Tom Hanks",
      "fields": [
        "actor",
        "supp",
        "cast"
      ]
    },
    "personId": 31,
    "years": "1984–Present",
    "customImage": "images/hubs/tom-hanks.jpg"
  },
  {
    "id": "tom-cruise",
    "active": true,
    "type": "Artist Hub",
    "name": "Tom Cruise",
    "shortName": "Tom Cruise",
    "desc": "Hollywood's last great movie star — charisma, intensity, and an unmatched commitment to spectacle.",
    "match": {
      "type": "name_in_credits",
      "value": "Tom Cruise",
      "fields": [
        "actor",
        "supp",
        "cast"
      ]
    },
    "personId": 500,
    "years": "1981–Present",
    "customImage": "images/hubs/tom-cruise.jpg"
  },
  {
    "id": "matt-damon",
    "active": true,
    "type": "Artist Hub",
    "name": "Matt Damon",
    "shortName": "Matt Damon",
    "desc": "From Good Will Hunting to the Bourne films to The Martian — one of his generation's most reliable leads.",
    "match": {
      "type": "name_in_credits",
      "value": "Matt Damon",
      "fields": [
        "actor",
        "supp",
        "cast"
      ]
    },
    "personId": 1892,
    "years": "1988–Present",
    "customImage": "images/hubs/matt-damon.jpg"
  },
  {
    "id": "eddie-murphy",
    "active": true,
    "type": "Artist Hub",
    "name": "Eddie Murphy",
    "shortName": "Eddie Murphy",
    "desc": "The defining comedic force of the 1980s — and a performer whose range only grew across the decades.",
    "match": {
      "type": "name_in_credits",
      "value": "Eddie Murphy",
      "fields": [
        "actor",
        "supp",
        "cast"
      ]
    },
    "personId": 776,
    "years": "1982–Present",
    "customImage": "images/hubs/eddie-murphy.jpg"
  }
]
